{
  "kind": "collectionType",
  "collectionName": "controladoras",
  "info": {
    "singularName": "controladora",
    "pluralName": "controladoras",
    "displayName": "Controladora",
    "description": ""
  },
  "options": {
    "draftAndPublish": true
  },
  "pluginOptions": {
    "i18n": {
      "localized": true
    }
  },
  "attributes": {
    "nombre": {
      "type": "string",
      "pluginOptions": {
        "i18n": {
          "localized": true
        }
      }
    },
    "generacion": {
      "type": "string",
      "pluginOptions": {
        "i18n": {
          "localized": true
        }
      }
    },
    "voltaje_entrada": {
      "type": "string",
      "pluginOptions": {
        "i18n": {
          "localized": true
        }
      }
    },
    "io_analogica": {
      "type": "string",
      "pluginOptions": {
        "i18n": {
          "localized": true
        }
      }
    },
    "comunicaciones": {
      "type": "string",
      "pluginOptions": {
        "i18n": {
          "localized": true
        }
      }
    },
    "expansiones_soportadas": {
      "type": "string",
      "pluginOptions": {
        "i18n": {
          "localized": true
        }
      }
    },
    "precio_lista": {
      "type": "string",
      "pluginOptions": {
        "i18n": {
          "localized": true
        }
      }
    },
    "ejes_max_soportados": {
      "type": "integer",
      "pluginOptions": {
        "i18n": {
          "localized": true
        }
      }
    },
    "peso_kg": {
      "type": "integer",
      "pluginOptions": {
        "i18n": {
          "localized": true
        }
      }
    },
    "dimensiones_mm": {
      "type": "string",
      "pluginOptions": {
        "i18n": {
          "localized": true
        }
      }
    },
    "grado_proteccion": {
      "type": "string",
      "pluginOptions": {
        "i18n": {
          "localized": true
        }
      }
    },
    "imagen": {
      "type": "media",
      "pluginOptions": {
        "i18n": {
          "localized": false
        }
      },
      "multiple": false,
      "required": false,
      "allowedTypes": [
        "images",
        "files",
        "videos",
        "audios"
      ]
    },
    "descripcion": {
      "type": "richtext",
      "pluginOptions": {
        "i18n": {
          "localized": true
        }
      }
    },
    "ficha_tecnica_pdf": {
      "type": "media",
      "pluginOptions": {
        "i18n": {
          "localized": true
        }
      },
      "multiple": false,
      "required": false,
      "allowedTypes": [
        "files"
      ]
    },
    "robots": {
      "type": "relation",
      "relation": "oneToMany",
      "target": "api::robot.robot",
      "mappedBy": "controladora"
    }
  }
}
